PurgeSecrets
